stemhat/Arial.ttf
stemhat/__init__.py
stemhat/core.py
stemhat-0.3.1.dist-info/LICENSE
stemhat-0.3.1.dist-info/METADATA
stemhat-0.3.1.dist-info/WHEEL
stemhat-0.3.1.dist-info/top_level.txt
stemhat-0.3.1.dist-info/RECORD
