Metadata-Version: 2.1
Name: stemhat
Version: 0.3.1
Summary: A library to control Cytron Pi StemHat
Home-page: https://github.com/Teakzieas/StemhatPython
Author: Cytron(Divyessh)
Author-email: divyesshev3@gmail.com
Classifier: Programming Language :: Python :: 3
Classifier: License :: OSI Approved :: MIT License
Classifier: Operating System :: OS Independent
Classifier: Programming Language :: Python :: 3 :: Only
Requires-Python: >=3.6
License-File: LICENSE
Requires-Dist: adafruit-blinka==8.52.0
Requires-Dist: adafruit-circuitpython-apds9960==3.1.14
Requires-Dist: adafruit-circuitpython-ssd1306==2.12.19
Requires-Dist: gpiozero==2.0.1
Requires-Dist: lgpio==0.2.2.0
Requires-Dist: pillow==11.1.0
Requires-Dist: smbus2==0.5.0
